{
  "package": "react",
  "start": "2025-11-22",
  "end": "2026-02-19",
  "downloads": [
    {
      "day": "2025-11-22",
      "downloads": 7125000
    },
    {
      "day": "2025-11-23",
      "downloads": 7125137
    },
    {
      "day": "2025-11-24",
      "downloads": 11500274
    },
    {
      "day": "2025-11-25",
      "downloads": 11500411
    },
    {
      "day": "2025-11-26",
      "downloads": 11500548
    },
    {
      "day": "2025-11-27",
      "downloads": 11500685
    },
    {
      "day": "2025-11-28",
      "downloads": 11500822
    },
    {
      "day": "2025-11-29",
      "downloads": 7125959
    },
    {
      "day": "2025-11-30",
      "downloads": 7126096
    },
    {
      "day": "2025-12-01",
      "downloads": 11501233
    },
    {
      "day": "2025-12-02",
      "downloads": 11501370
    },
    {
      "day": "2025-12-03",
      "downloads": 11501507
    },
    {
      "day": "2025-12-04",
      "downloads": 11501644
    },
    {
      "day": "2025-12-05",
      "downloads": 11501781
    },
    {
      "day": "2025-12-06",
      "downloads": 7126918
    },
    {
      "day": "2025-12-07",
      "downloads": 7127055
    },
    {
      "day": "2025-12-08",
      "downloads": 11502192
    },
    {
      "day": "2025-12-09",
      "downloads": 11502329
    },
    {
      "day": "2025-12-10",
      "downloads": 11502466
    },
    {
      "day": "2025-12-11",
      "downloads": 11502603
    },
    {
      "day": "2025-12-12",
      "downloads": 11502740
    },
    {
      "day": "2025-12-13",
      "downloads": 7127877
    },
    {
      "day": "2025-12-14",
      "downloads": 7128014
    },
    {
      "day": "2025-12-15",
      "downloads": 11503151
    },
    {
      "day": "2025-12-16",
      "downloads": 11503288
    },
    {
      "day": "2025-12-17",
      "downloads": 11503425
    },
    {
      "day": "2025-12-18",
      "downloads": 11503562
    },
    {
      "day": "2025-12-19",
      "downloads": 11503699
    },
    {
      "day": "2025-12-20",
      "downloads": 7128836
    },
    {
      "day": "2025-12-21",
      "downloads": 7128973
    },
    {
      "day": "2025-12-22",
      "downloads": 11504110
    },
    {
      "day": "2025-12-23",
      "downloads": 11504247
    },
    {
      "day": "2025-12-24",
      "downloads": 11504384
    },
    {
      "day": "2025-12-25",
      "downloads": 11504521
    },
    {
      "day": "2025-12-26",
      "downloads": 11504658
    },
    {
      "day": "2025-12-27",
      "downloads": 7129795
    },
    {
      "day": "2025-12-28",
      "downloads": 7129932
    },
    {
      "day": "2025-12-29",
      "downloads": 11505069
    },
    {
      "day": "2025-12-30",
      "downloads": 11505206
    },
    {
      "day": "2025-12-31",
      "downloads": 11505343
    },
    {
      "day": "2026-01-01",
      "downloads": 11505480
    },
    {
      "day": "2026-01-02",
      "downloads": 11505617
    },
    {
      "day": "2026-01-03",
      "downloads": 7130754
    },
    {
      "day": "2026-01-04",
      "downloads": 7130891
    },
    {
      "day": "2026-01-05",
      "downloads": 11506028
    },
    {
      "day": "2026-01-06",
      "downloads": 11506165
    },
    {
      "day": "2026-01-07",
      "downloads": 11506302
    },
    {
      "day": "2026-01-08",
      "downloads": 11506439
    },
    {
      "day": "2026-01-09",
      "downloads": 11506576
    },
    {
      "day": "2026-01-10",
      "downloads": 7131713
    },
    {
      "day": "2026-01-11",
      "downloads": 7131850
    },
    {
      "day": "2026-01-12",
      "downloads": 11506987
    },
    {
      "day": "2026-01-13",
      "downloads": 11507124
    },
    {
      "day": "2026-01-14",
      "downloads": 11507261
    },
    {
      "day": "2026-01-15",
      "downloads": 11507398
    },
    {
      "day": "2026-01-16",
      "downloads": 11507535
    },
    {
      "day": "2026-01-17",
      "downloads": 7132672
    },
    {
      "day": "2026-01-18",
      "downloads": 7132809
    },
    {
      "day": "2026-01-19",
      "downloads": 11507946
    },
    {
      "day": "2026-01-20",
      "downloads": 11508083
    },
    {
      "day": "2026-01-21",
      "downloads": 11508220
    },
    {
      "day": "2026-01-22",
      "downloads": 11508357
    },
    {
      "day": "2026-01-23",
      "downloads": 11508494
    },
    {
      "day": "2026-01-24",
      "downloads": 7133631
    },
    {
      "day": "2026-01-25",
      "downloads": 7133768
    },
    {
      "day": "2026-01-26",
      "downloads": 11508905
    },
    {
      "day": "2026-01-27",
      "downloads": 11509042
    },
    {
      "day": "2026-01-28",
      "downloads": 11509179
    },
    {
      "day": "2026-01-29",
      "downloads": 11509316
    },
    {
      "day": "2026-01-30",
      "downloads": 11509453
    },
    {
      "day": "2026-01-31",
      "downloads": 7134590
    },
    {
      "day": "2026-02-01",
      "downloads": 7134727
    },
    {
      "day": "2026-02-02",
      "downloads": 11509864
    },
    {
      "day": "2026-02-03",
      "downloads": 11510001
    },
    {
      "day": "2026-02-04",
      "downloads": 11510138
    },
    {
      "day": "2026-02-05",
      "downloads": 11510275
    },
    {
      "day": "2026-02-06",
      "downloads": 11510412
    },
    {
      "day": "2026-02-07",
      "downloads": 7135549
    },
    {
      "day": "2026-02-08",
      "downloads": 7135686
    },
    {
      "day": "2026-02-09",
      "downloads": 11510823
    },
    {
      "day": "2026-02-10",
      "downloads": 11510960
    },
    {
      "day": "2026-02-11",
      "downloads": 11511097
    },
    {
      "day": "2026-02-12",
      "downloads": 11511234
    },
    {
      "day": "2026-02-13",
      "downloads": 11511371
    },
    {
      "day": "2026-02-14",
      "downloads": 7136508
    },
    {
      "day": "2026-02-15",
      "downloads": 7136645
    },
    {
      "day": "2026-02-16",
      "downloads": 11511782
    },
    {
      "day": "2026-02-17",
      "downloads": 11511919
    },
    {
      "day": "2026-02-18",
      "downloads": 11512056
    },
    {
      "day": "2026-02-19",
      "downloads": 11512193
    }
  ]
}
